spg/__init__.py
spg/spotify_playlist_generator.py
spotify_playlist_generator_1-0.0.3.dist-info/LICENSE
spotify_playlist_generator_1-0.0.3.dist-info/METADATA
spotify_playlist_generator_1-0.0.3.dist-info/WHEEL
spotify_playlist_generator_1-0.0.3.dist-info/top_level.txt
spotify_playlist_generator_1-0.0.3.dist-info/RECORD
