Metadata-Version: 2.1
Name: spotify-playlist-generator-1
Version: 0.0.3
Summary: A simple to use spotify playlist generator
Home-page: https://github.com/danielchukwu/spotify-playlist-generator
Author: Daniel
Author-email: 00chukwudaniel@gmail.com
Project-URL: Bug Tracker, https://github.com/danielchukwu/spotify-playlist-generator/issues
Classifier: Programming Language :: Python :: 3
Classifier: License :: OSI Approved :: MIT License
Classifier: Operating System :: OS Independent
Requires-Python: >=3.6
License-File: LICENSE
